.gitignore
LICENSE
README.md
pyproject.toml
.github/workflows/python-publish.yml
src/blendipose/__init__.py
src/blendipose/_version.py
src/blendipose/renderer.py
src/blendipose/util.py
src/blendipose.egg-info/PKG-INFO
src/blendipose.egg-info/SOURCES.txt
src/blendipose.egg-info/dependency_links.txt
src/blendipose.egg-info/requires.txt
src/blendipose.egg-info/top_level.txt
src/blendipose/blendify/README.md
src/blendipose/blendify/__init__.py
src/blendipose/blendify/scene.py
src/blendipose/blendify/cameras/__init__.py
src/blendipose/blendify/cameras/base.py
src/blendipose/blendify/cameras/common.py
src/blendipose/blendify/cameras/warping.py
src/blendipose/blendify/colors/__init__.py
src/blendipose/blendify/colors/base.py
src/blendipose/blendify/colors/common.py
src/blendipose/blendify/colors/texture.py
src/blendipose/blendify/internal/__init__.py
src/blendipose/blendify/internal/io.py
src/blendipose/blendify/internal/parser.py
src/blendipose/blendify/internal/positionable.py
src/blendipose/blendify/internal/singleton.py
src/blendipose/blendify/internal/texture.py
src/blendipose/blendify/internal/types.py
src/blendipose/blendify/lights/__init__.py
src/blendipose/blendify/lights/area.py
src/blendipose/blendify/lights/base.py
src/blendipose/blendify/lights/collection.py
src/blendipose/blendify/lights/common.py
src/blendipose/blendify/materials/__init__.py
src/blendipose/blendify/materials/base.py
src/blendipose/blendify/materials/bsdf.py
src/blendipose/blendify/materials/emission.py
src/blendipose/blendify/materials/metal.py
src/blendipose/blendify/materials/plastic.py
src/blendipose/blendify/materials/wireframe.py
src/blendipose/blendify/renderables/__init__.py
src/blendipose/blendify/renderables/base.py
src/blendipose/blendify/renderables/collection.py
src/blendipose/blendify/renderables/mesh.py
src/blendipose/blendify/renderables/pointcloud.py
src/blendipose/blendify/renderables/primitives.py
src/blendipose/blendify/utils/__init__.py
src/blendipose/blendify/utils/camera_trajectory.py
src/blendipose/blendify/utils/image.py
src/blendipose/blendify/utils/pointcloud.py
src/blendipose/blendify/utils/shadow_catcher.py
