Metadata-Version: 2.4
Name: blendipose
Version: 0.1.2
Summary: Render human motion sequences with Blender, with or without overlaying on a video
Author-email: István Sárándi <istvan.sarandi@uni-tuebingen.de>
License-Expression: GPL-3.0-only
Project-URL: Homepage, https://github.com/isarandi/blendipose
Project-URL: Repository, https://github.com/isarandi/blendipose
Project-URL: Issues, https://github.com/isarandi/blendipose/issues
Classifier: Development Status :: 4 - Beta
Classifier: Programming Language :: Python
Classifier: Programming Language :: Python :: 3
Classifier: Operating System :: POSIX :: Linux
Requires-Python: >=3.10
License-File: LICENSE
Requires-Dist: numpy
Requires-Dist: numba
Requires-Dist: opencv-python
Requires-Dist: shapely
Requires-Dist: trimesh
Requires-Dist: cameravision
Requires-Dist: simplepyutils
Requires-Dist: framepump
Requires-Dist: scipy
Requires-Dist: bpy==3.6.0
Dynamic: license-file
